awslabs/__init__.py
awslabs/cloudwatch_mcp_server/__init__.py
awslabs/cloudwatch_mcp_server/aws_common.py
awslabs/cloudwatch_mcp_server/common.py
awslabs/cloudwatch_mcp_server/server.py
awslabs/cloudwatch_mcp_server/cloudwatch_alarms/models.py
awslabs/cloudwatch_mcp_server/cloudwatch_alarms/tools.py
awslabs/cloudwatch_mcp_server/cloudwatch_logs/models.py
awslabs/cloudwatch_mcp_server/cloudwatch_logs/tools.py
awslabs/cloudwatch_mcp_server/cloudwatch_metrics/cloudformation_template_generator.py
awslabs/cloudwatch_mcp_server/cloudwatch_metrics/constants.py
awslabs/cloudwatch_mcp_server/cloudwatch_metrics/metric_analyzer.py
awslabs/cloudwatch_mcp_server/cloudwatch_metrics/metric_data_decomposer.py
awslabs/cloudwatch_mcp_server/cloudwatch_metrics/models.py
awslabs/cloudwatch_mcp_server/cloudwatch_metrics/tools.py
awslabs/cloudwatch_mcp_server/cloudwatch_metrics/data/metric_metadata.json
awslabs_cloudwatch_mcp_server-0.0.18.dist-info/METADATA
awslabs_cloudwatch_mcp_server-0.0.18.dist-info/WHEEL
awslabs_cloudwatch_mcp_server-0.0.18.dist-info/entry_points.txt
awslabs_cloudwatch_mcp_server-0.0.18.dist-info/licenses/LICENSE
awslabs_cloudwatch_mcp_server-0.0.18.dist-info/licenses/NOTICE
awslabs_cloudwatch_mcp_server-0.0.18.dist-info/RECORD
