Metadata-Version: 2.4
Name: awslabs.cloudwatch-mcp-server
Version: 0.0.18
Summary: An AWS Labs Model Context Protocol (MCP) server for cloudwatch
Project-URL: homepage, https://awslabs.github.io/mcp/
Project-URL: docs, https://awslabs.github.io/mcp/servers/cloudwatch-mcp-server/
Project-URL: documentation, https://awslabs.github.io/mcp/servers/cloudwatch-mcp-server/
Project-URL: repository, https://github.com/awslabs/mcp.git
Project-URL: changelog, https://github.com/awslabs/mcp/blob/main/src/cloudwatch-mcp-server/CHANGELOG.md
Author: Amazon Web Services
Author-email: AWSLabs MCP <203918161+awslabs-mcp@users.noreply.github.com>, Isaiah Lemmon <ilemmon@amazon.com>, Shrikant Tambe <tshrikan@amazon.com>, Gianluca Cacace <cacaceg@amazon.com>, Andrea Giuliano <aggiulia@amazon.com>, Goran Modrusa <goran@amazon.com>
License: Apache-2.0
License-File: LICENSE
License-File: NOTICE
Classifier: License :: OSI Approved :: Apache Software License
Classifier: Operating System :: OS Independent
Classifier: Programming Language :: Python
Classifier: Programming Language :: Python :: 3
Classifier: Programming Language :: Python :: 3.10
Classifier: Programming Language :: Python :: 3.11
Classifier: Programming Language :: Python :: 3.12
Classifier: Programming Language :: Python :: 3.13
Requires-Python: >=3.10
Requires-Dist: boto3>=1.38.22
Requires-Dist: loguru>=0.7.0
Requires-Dist: mcp[cli]>=1.23.0
Requires-Dist: numpy>=2.0.0
Requires-Dist: pandas>=2.2.3
Requires-Dist: pydantic>=2.10.6
Requires-Dist: statsmodels>=0.14.0
